[
  {
    "filename": "DSCF8601_副本.JPG",
    "cameraModel": "X-E3",
    "lensModel": "XF23mmF1.4 R",
    "focalLength": "23 mm",
    "iso": 250,
    "aperture": "f/1.4",
    "shutterSpeed": "1/60",
    "dateTaken": "2026-04-03T00:05:48",
    "width": 800,
    "height": 533,
    "id": 1
  },
  {
    "filename": "DSCF8604_副本.JPG",
    "cameraModel": "X-E3",
    "lensModel": "XF23mmF1.4 R",
    "focalLength": "23 mm",
    "iso": 250,
    "aperture": "f/1.4",
    "shutterSpeed": "1/60",
    "dateTaken": "2026-04-04T15:57:45",
    "width": 800,
    "height": 533,
    "id": 2
  },
  {
    "filename": "DSCF8605_副本.JPG",
    "cameraModel": "X-E3",
    "lensModel": "XF23mmF1.4 R",
    "focalLength": "23 mm",
    "iso": 200,
    "aperture": "f/4.5",
    "shutterSpeed": "1/150",
    "dateTaken": "2026-04-04T17:33:29",
    "width": 800,
    "height": 533,
    "id": 3
  },
  {
    "filename": "DSCF8607_副本.JPG",
    "cameraModel": "X-E3",
    "lensModel": "XF23mmF1.4 R",
    "focalLength": "23 mm",
    "iso": 200,
    "aperture": "f/5.6",
    "shutterSpeed": "1/640",
    "dateTaken": "2026-04-04T17:34:41",
    "width": 800,
    "height": 533,
    "id": 4
  },
  {
    "filename": "DSCF8608_副本.JPG",
    "cameraModel": "X-E3",
    "lensModel": "XF23mmF1.4 R",
    "focalLength": "23 mm",
    "iso": 200,
    "aperture": "f/1.4",
    "shutterSpeed": "1/7500",
    "dateTaken": "2026-04-04T17:41:17",
    "width": 800,
    "height": 533,
    "id": 5
  },
  {
    "filename": "DSCF8609_副本.JPG",
    "cameraModel": "X-E3",
    "lensModel": "XF23mmF1.4 R",
    "focalLength": "23 mm",
    "iso": 200,
    "aperture": "f/5.6",
    "shutterSpeed": "1/950",
    "dateTaken": "2026-04-04T17:42:09",
    "width": 800,
    "height": 533,
    "id": 6
  },
  {
    "filename": "DSCF8610_副本.JPG",
    "cameraModel": "X-E3",
    "lensModel": "XF23mmF1.4 R",
    "focalLength": "23 mm",
    "iso": 200,
    "aperture": "f/5.6",
    "shutterSpeed": "1/750",
    "dateTaken": "2026-04-04T17:42:10",
    "width": 800,
    "height": 533,
    "id": 7
  },
  {
    "filename": "DSCF8611_副本.JPG",
    "cameraModel": "X-E3",
    "lensModel": "XF23mmF1.4 R",
    "focalLength": "23 mm",
    "iso": 200,
    "aperture": "f/1.4",
    "shutterSpeed": "1/800",
    "dateTaken": "2026-04-04T17:56:33",
    "width": 800,
    "height": 533,
    "id": 8
  },
  {
    "filename": "DSCF8612_副本.JPG",
    "cameraModel": "X-E3",
    "lensModel": "XF23mmF1.4 R",
    "focalLength": "23 mm",
    "iso": 200,
    "aperture": "f/1.4",
    "shutterSpeed": "1/16000",
    "dateTaken": "2026-04-04T18:16:09",
    "width": 800,
    "height": 533,
    "id": 9
  },
  {
    "filename": "DSCF8613_副本.JPG",
    "cameraModel": "X-E3",
    "lensModel": "XF23mmF1.4 R",
    "focalLength": "23 mm",
    "iso": 200,
    "aperture": "f/1.4",
    "shutterSpeed": "1/3800",
    "dateTaken": "2026-04-04T18:24:01",
    "width": 800,
    "height": 533,
    "id": 10
  },
  {
    "filename": "DSCF8614_副本.JPG",
    "cameraModel": "X-E3",
    "lensModel": "XF23mmF1.4 R",
    "focalLength": "23 mm",
    "iso": 200,
    "aperture": "f/1.4",
    "shutterSpeed": "1/6000",
    "dateTaken": "2026-04-04T18:27:22",
    "width": 800,
    "height": 533,
    "id": 11
  },
  {
    "filename": "DSCF8664_副本.JPG",
    "cameraModel": "X-E3",
    "lensModel": "XF23mmF1.4 R",
    "focalLength": "23 mm",
    "iso": 200,
    "aperture": "f/5.6",
    "shutterSpeed": "1/340",
    "dateTaken": "2026-04-05T00:24:37",
    "width": 800,
    "height": 533,
    "id": 12
  },
  {
    "filename": "DSCF8665_副本.JPG",
    "cameraModel": "X-E3",
    "lensModel": "XF23mmF1.4 R",
    "focalLength": "23 mm",
    "iso": 200,
    "aperture": "f/5.6",
    "shutterSpeed": "1/220",
    "dateTaken": "2026-04-05T00:24:47",
    "width": 800,
    "height": 533,
    "id": 13
  },
  {
    "filename": "DSCF8666_副本.JPG",
    "cameraModel": "X-E3",
    "lensModel": "XF23mmF1.4 R",
    "focalLength": "23 mm",
    "iso": 200,
    "aperture": "f/1.4",
    "shutterSpeed": "1/8500",
    "dateTaken": "2026-04-05T00:24:53",
    "width": 800,
    "height": 533,
    "id": 14
  },
  {
    "filename": "DSCF8667_副本.JPG",
    "cameraModel": "X-E3",
    "lensModel": "XF23mmF1.4 R",
    "focalLength": "23 mm",
    "iso": 200,
    "aperture": "f/5.6",
    "shutterSpeed": "1/500",
    "dateTaken": "2026-04-05T00:25:28",
    "width": 800,
    "height": 533,
    "id": 15
  },
  {
    "filename": "DSCF8668_副本.JPG",
    "cameraModel": "X-E3",
    "lensModel": "XF23mmF1.4 R",
    "focalLength": "23 mm",
    "iso": 200,
    "aperture": "f/5.6",
    "shutterSpeed": "1/200",
    "dateTaken": "2026-04-05T00:28:13",
    "width": 800,
    "height": 533,
    "id": 16
  },
  {
    "filename": "DSCF8669_副本.JPG",
    "cameraModel": "X-E3",
    "lensModel": "XF23mmF1.4 R",
    "focalLength": "23 mm",
    "iso": 200,
    "aperture": "f/5.6",
    "shutterSpeed": "1/125",
    "dateTaken": "2026-04-05T00:28:25",
    "width": 800,
    "height": 533,
    "id": 17
  },
  {
    "filename": "DSCF8670_副本.JPG",
    "cameraModel": "X-E3",
    "lensModel": "XF23mmF1.4 R",
    "focalLength": "23 mm",
    "iso": 200,
    "aperture": "f/5.6",
    "shutterSpeed": "1/140",
    "dateTaken": "2026-04-05T00:28:28",
    "width": 800,
    "height": 533,
    "id": 18
  },
  {
    "filename": "DSCF8671_副本.JPG",
    "cameraModel": "X-E3",
    "lensModel": "XF23mmF1.4 R",
    "focalLength": "23 mm",
    "iso": 200,
    "aperture": "f/1.4",
    "shutterSpeed": "1/2500",
    "dateTaken": "2026-04-05T00:28:47",
    "width": 800,
    "height": 533,
    "id": 19
  },
  {
    "filename": "DSCF8672_副本.JPG",
    "cameraModel": "X-E3",
    "lensModel": "XF23mmF1.4 R",
    "focalLength": "23 mm",
    "iso": 200,
    "aperture": "f/1.4",
    "shutterSpeed": "1/2700",
    "dateTaken": "2026-04-05T00:28:51",
    "width": 800,
    "height": 533,
    "id": 20
  },
  {
    "filename": "DSCF8673_副本.JPG",
    "cameraModel": "X-E3",
    "lensModel": "XF23mmF1.4 R",
    "focalLength": "23 mm",
    "iso": 200,
    "aperture": "f/1.4",
    "shutterSpeed": "1/2700",
    "dateTaken": "2026-04-05T00:28:53",
    "width": 800,
    "height": 533,
    "id": 21
  },
  {
    "filename": "DSCF8674_副本.JPG",
    "cameraModel": "X-E3",
    "lensModel": "XF56mmF1.2 R",
    "focalLength": "56 mm",
    "iso": 200,
    "aperture": "f/16.0",
    "shutterSpeed": "1/160",
    "dateTaken": "2026-04-05T00:32:13",
    "width": 800,
    "height": 533,
    "id": 22
  },
  {
    "filename": "DSCF8675_副本.JPG",
    "cameraModel": "X-E3",
    "lensModel": "XF56mmF1.2 R",
    "focalLength": "56 mm",
    "iso": 200,
    "aperture": "f/16.0",
    "shutterSpeed": "1/110",
    "dateTaken": "2026-04-05T00:32:46",
    "width": 800,
    "height": 533,
    "id": 23
  },
  {
    "filename": "DSCF8676_副本.JPG",
    "cameraModel": "X-E3",
    "lensModel": "XF56mmF1.2 R",
    "focalLength": "56 mm",
    "iso": 200,
    "aperture": "f/16.0",
    "shutterSpeed": "1/120",
    "dateTaken": "2026-04-05T00:32:55",
    "width": 800,
    "height": 533,
    "id": 24
  },
  {
    "filename": "DSCF8677_副本.JPG",
    "cameraModel": "X-E3",
    "lensModel": "XF56mmF1.2 R",
    "focalLength": "56 mm",
    "iso": 200,
    "aperture": "f/16.0",
    "shutterSpeed": "1/105",
    "dateTaken": "2026-04-05T00:33:02",
    "width": 800,
    "height": 533,
    "id": 25
  },
  {
    "filename": "DSCF8678_副本.JPG",
    "cameraModel": "X-E3",
    "lensModel": "XF56mmF1.2 R",
    "focalLength": "56 mm",
    "iso": 200,
    "aperture": "f/16.0",
    "shutterSpeed": "1/110",
    "dateTaken": "2026-04-05T00:33:12",
    "width": 800,
    "height": 533,
    "id": 26
  },
  {
    "filename": "DSCF8679_副本.JPG",
    "cameraModel": "X-E3",
    "lensModel": "XF56mmF1.2 R",
    "focalLength": "56 mm",
    "iso": 200,
    "aperture": "f/16.0",
    "shutterSpeed": "1/105",
    "dateTaken": "2026-04-05T00:33:15",
    "width": 800,
    "height": 533,
    "id": 27
  },
  {
    "filename": "DSCF8680_副本.JPG",
    "cameraModel": "X-E3",
    "lensModel": "XF56mmF1.2 R",
    "focalLength": "56 mm",
    "iso": 200,
    "aperture": "f/16.0",
    "shutterSpeed": "1/200",
    "dateTaken": "2026-04-05T00:33:21",
    "width": 800,
    "height": 533,
    "id": 28
  },
  {
    "filename": "DSCF8681_副本.JPG",
    "cameraModel": "X-E3",
    "lensModel": "XF56mmF1.2 R",
    "focalLength": "56 mm",
    "iso": 200,
    "aperture": "f/16.0",
    "shutterSpeed": "1/125",
    "dateTaken": "2026-04-05T00:33:45",
    "width": 800,
    "height": 533,
    "id": 29
  }
]